{"name":"Japan","iso3":"JPN","iso2":"JP","phone_code":"81","capital":"Tokyo","currency":"JPY","currency_name":"Japanese yen","currency_symbol":"\u00a5","emoji":"\ud83c\uddef\ud83c\uddf5","emojiU":"U+1F1EF U+1F1F5","translations":{"kr":"\uc77c\ubcf8","br":"Jap\u00e3o","pt":"Jap\u00e3o","nl":"Japan","hr":"Japan","fa":"\u0698\u0627\u067e\u0646","de":"Japan","es":"Jap\u00f3n","fr":"Japon","ja":"\u65e5\u672c","it":"Giappone","cn":"\u65e5\u672c","tr":"Japonya"},"states":[{"name":"Aichi Prefecture","state_code":"23","cities":["Aisai-shi","Ama-gun","Anj\u014d-shi","Chiry\u016b","Chiry\u016b-shi","Chita","Chita-shi","Gamag\u014dri","Gamag\u014dri-shi","Handa","Handa-shi","Hekinan","Hekinan-shi","Ichinomiya","Ichinomiya-shi","Inazawa","Inazawa-shi","Inuyama","Inuyama-shi","Ishiki","Iwakura","Iwakura-shi","Kanie","Kariya","Kariya-shi","Kasugai","Kasugai-shi","Kitanagoya","Kitanagoya-shi","Kiyosu-shi","Komaki","Komaki-shi","K\u014dnan","K\u014dnan-shi","Kozakai-ch\u014d","Kuroda","Miyoshi-shi","Nagakute-shi","Nagoya","Nishio","Nishio-shi","Nisshin-shi","\u014cbu","\u014cbu-shi","Okazaki-shi","Owariasahi-shi","Seto","Seto-shi","Shinshiro","Shinshiro-shi","Sobue","Tahara","Tahara-shi","Takahama","Takahama-shi","Taketoyo","T\u014dkai-shi","Tokoname","Tokoname-shi","Toyoake","Toyoake-shi","Toyohama","Toyohashi","Toyohashi-shi","Toyokawa","Toyokawa-shi","Toyota-shi","Tsushima","Tsushima-shi","Yatomi-shi"]},{"name":"Akita Prefecture","state_code":"05","cities":["Akita","Akita Shi","Daisen","Daisen-shi","Hanawa","Kakunodatemachi","Katagami","Katagami-shi","Kazuno Shi","Kitaakita-shi","Nikaho-shi","Noshiro","Noshiro Shi","\u014cdate","\u014cdate-shi","Oga","Oga-shi","\u014cmagari","Semboku-shi","Takanosu","Tenn\u014d","Yokote","Yokote-shi","Yurihonj\u014d","Yurihonj\u014d-shi","Yuzawa","Yuzawa-shi"]},{"name":"Aomori Prefecture","state_code":"02","cities":["Aomori","Aomori Shi","Goshogawara","Goshogawara Shi","Hachinohe","Hachinohe Shi","Hirakawa","Hirakawa Shi","Hirosaki","Hirosaki Shi","Kuroishi","Kuroishi Shi","Misawa","Misawa Shi","Mutsu","Mutsu-shi","Namioka","Shimokizukuri","Towada Shi","Tsugaru","Tsugaru Shi"]},{"name":"Chiba Prefecture","state_code":"12","cities":["Abiko","Abiko-shi","Asahi-shi","Chiba","Ch\u014dshi-shi","Funabashi-shi","Futtsu","Hasaki","Honch\u014d","Ichihara","Ichihara Shi","Ichikawa Shi","Inzai-shi","Isumi","Isumi Shi","Kamagaya Shi","Kamogawa","Kamogawa-shi","Kashiwa","Kashiwa Shi","Katori-shi","Katsuura","Katsuura-shi","Kimitsu","Kisarazu","Kisarazu Shi","Matsudo Shi","Minamib\u014ds\u014d Shi","Mobara","Mobara Shi","Nagareyama","Nagareyama-shi","Narashino-shi","Narita","Narita-shi","Narut\u014d","Noda","Noda-shi","\u014cami","\u014camishirasato-shi","\u014chara","Omigawa","Sakura","Sakura-shi","Sambu-gun","Sanmu","Sanmu-shi","Sawara","Shiroi","Shiroi-shi","Shisui","Sodegaura-shi","S\u014dsa-shi","Tateyama","Tateyama-shi","T\u014dgane","T\u014dgane-shi","Tomisato-shi","Urayasu-shi","Yachimata","Yachimata-shi","Yachiyo-shi","Y\u014dkaichiba","Yotsukaid\u014d","Yotsukaid\u014d-shi"]},{"name":"Ehime Prefecture","state_code":"38","cities":["H\u014dj\u014d","Imabari-shi","Iyo","Iyo-shi","Kawanoech\u014d","Kihoku-ch\u014d","Masaki-ch\u014d","Matsuyama-shi","Niihama","Niihama-shi","\u014czu","\u014czu-shi","Saij\u014d","Saij\u014d-shi","Seiyo-shi","Shikoku-ch\u016b\u014d Shi","T\u014don-shi","Uwajima","Uwajima-shi","Yawatahama-shi"]},{"name":"Fukui Prefecture","state_code":"18","cities":["Asahi","Awara-shi","Echizen-shi","Fukui-shi","Katsuyama","Katsuyama Shi","Maruoka","Mikuni","Obama","Obama-shi","\u014ci-gun","Ono","\u014cno-shi","Sabae","Sabae-shi","Sakai-shi","Takefu","Tsuruga","Tsuruga-shi"]},{"name":"Fukuoka Prefecture","state_code":"40","cities":["Amagi","Asakura Shi","Buzen","Buzen-shi","Chikugo Shi","Chikushino-shi","Dazaifu-shi","Fukuoka","Fukuoka-shi","Fukutsu Shi","Iizuka","Iizuka Shi","Itoshima-shi","Kama Shi","Kanda","Kasuga Shi","Kawasaki","Kitakyushu","Koga","Koga-shi","Kurume","Kurume Shi","Maebaru-ch\u016b\u014d","Miyama Shi","Miyata","Miyawaka Shi","Munakata-shi","Nakama","Nakama Shi","Nishifukuma","N\u014dgata","N\u014dgata Shi","Og\u014dri-shi","\u014ckawa","\u014ckawa-shi","\u014cmuta","\u014cmuta Shi","Onga-gun","\u014cnoj\u014d","\u014cnoj\u014d Shi","Sasaguri","Setakamachi-takayanagi","Shiida","Shing\u016b","Tagawa","Tagawa Shi","Tanushimarumachi-toyoki","Tsuiki","Ukiha Shi","Umi","Yame Shi","Yanagawa","Yanagawa Shi","Yoshitomi","Yukuhashi","Yukuhashi Shi"]},{"name":"Fukushima Prefecture","state_code":"07","cities":["Aizu-wakamatsu Shi","Date-shi","Fukushima","Fukushima Shi","Funehikimachi-funehiki","Hobaramachi","Inawashiro","Ishikawa","Iwaki","Iwaki-shi","Kitakata","Kitakata-shi","K\u014driyama","K\u014driyama Shi","Miharu","Minami-S\u014dma","Minamis\u014dma Shi","Motomiya","Motomiya-shi","Namie","Nihommatsu","Nihonmatsu Shi","Shirakawa Shi","S\u014dma","S\u014dma Shi","Sukagawa","Sukagawa Shi","Tamura","Tamura-shi","Yanagawamachi-saiwaich\u014d"]},{"name":"Gifu Prefecture","state_code":"21","cities":["Ena-shi","Gero","Gero-shi","Gifu-shi","G\u014ddo","Guj\u014d","Guj\u014d-shi","Hashima","Hashima-shi","Hida","Hida Shi","Kaizu-shi","Kakamigahara-shi","Kani-shi","Kasamatsuch\u014d","Mino","Mino-shi","Minokamo","Minokamo-shi","Mitake","Mizuho-shi","Mizunami","Mizunami-shi","Motosu-shi","Nakatsugawa","Nakatsugawa-shi","\u014cgaki-shi","Seki-shi","Tajimi","Tajimi-shi","Takayama Shi","Tarui","Toki","Toki-shi","Yamagata-shi"]},{"name":"Gunma Prefecture","state_code":"10","cities":["Agatsuma-gun","Annaka","Annaka Shi","Fujioka","Fujioka Shi","Isesaki","Isesaki Shi","Kanekomachi","Kiry\u016b","Kiry\u016b Shi","Maebashi","Maebashi Shi","Midori","Midori Shi","Nakanoj\u014dmachi","Numata","Numata Shi","\u014cmamach\u014d-\u014dmama","\u014cta","\u014cta-shi","Sakai-nakajima","Shibukawa","Shibukawa-shi","Takasaki","Takasaki Shi","Tamamura","Tatebayashi","Tatebayashi-shi","Tomioka","Tomioka-shi","Yoshii"]},{"name":"Hiroshima Prefecture","state_code":"34","cities":["Aki-takata Shi","Etajima-shi","Fuch\u016b-shi","Fuch\u016bch\u014d","Fukuyama","Fukuyama Shi","Hatsukaichi","Hatsukaichi-shi","Higashihiroshima Shi","Hiroshima","Hiroshima-shi","Innoshima","Kannabech\u014d-yahiro","Kure","Kure-shi","Mihara","Mihara Shi","Miyajima","Miyoshi","Miyoshi Shi","\u014cno-hara","Onomichi","Onomichi-shi","\u014ctake","\u014ctake-shi","Shin\u2019ichi","Sh\u014dbara","Sh\u014dbara-shi","Takehara","Takehara-shi"]},{"name":"Hokkaid\u014d Prefecture","state_code":"01","cities":["Abashiri","Abashiri Shi","Akabira","Akabira-shi","Asahikawa","Ashibetsu","Ashibetsu-shi","Bibai","Chitose","Chitose Shi","Date","Date-shi","Ebetsu","Eniwa-shi","Fukagawa","Fukagawa-shi","Furano-shi","Hakodate","Hakodate Shi","Hokuto","Hokuto-shi","Honch\u014d","Ishikari","Ishikari-shi","Iwamizawa","Iwamizawa-shi","Iwanai","Kamiiso","Kamikawa","Kitahiroshima","Kitahiroshima-shi","Kitami","Ktiami Shi","Kushiro","Kushiro Shi","Makubetsu","Mikasa","Mikasa-shi","Mombetsu","Monbetsu Shi","Motomachi","Muroran","Muroran-shi","Nayoro","Nayoro Shi","Nemuro","Nemuro-shi","Niseko Town","Noboribetsu","Noboribetsu-shi","Obihiro","Obihiro Shi","Otaru","Otaru-shi","Otofuke","Rebun Gun","Rishiri Gun","Rishiri Town","Rumoi","Rumoi-shi","Sapporo","Sapporo-shi","Shibetsu","Shibetsu Shi","Shimo-furano","Shiraoi","Shizunai-furukawach\u014d","Sunagawa","Sunagawa-shi","Takikawa","Takikawa-shi","T\u014dbetsu","Tomakomai","Tomakomai Shi","Utashinai","Utashinai-shi","Wakkanai","Wakkanai Shi","Yoichi","Y\u016bbari","Y\u016bbari-shi"]},{"name":"Hy\u014dgo Prefecture","state_code":"28","cities":["Aioi","Aioi Shi","Akashi","Akashi Shi","Amagasaki Shi","Asago-shi","Ashiya","Ashiya Shi","Awaji Shi","Fukura","Himeji","Himeji Shi","Itami","Itami Shi","Kakogawa Shi","Kakogawach\u014d-honmachi","Kariya","Kasai Shi","Kat\u014d Shi","Kawanishi","Kawanishi Shi","Kobe","Miki","Miki Shi","Minamiawaji Shi","Nishinomiya Shi","Nishinomiya-hama","Nishiwaki","Nishiwaki-shi","Ono","Ono Shi","Sanda Shi","Sandach\u014d","Sasayama","Sasayama-shi","Shirahamach\u014d-usazakiminami","Shis\u014d-shi","Sumoto","Sumoto Shi","Taka-gun","Takarazuka","Takarazuka Shi","Takasago Shi","Tanba-shi","Tatsuno-shi","Tatsunoch\u014d-tominaga","Toyooka","Toyooka-shi","Yabu","Yabu-shi","Yamazakich\u014d-nakabirose","Yashiro","Yonedacho Sendo"]},{"name":"Ibaraki Prefecture","state_code":"08","cities":["Ami","Band\u014d","Band\u014d-shi","Chikusei","Chikusei-shi","Daigo","Edosaki","Fujishiro","Funaishikawa","Hitachi","Hitachi-Naka","Hitachi-ota","Hitachi-shi","Hitachinaka-shi","Hitachi\u014dmiya-shi","Hitachi\u014dta-shi","Hokota-shi","Inashiki","Inashiki-shi","Ishige","Ishioka","Ishioka-shi","Itako","Itako-shi","Iwai","Iwase","J\u014ds\u014d-shi","Kamisu-shi","Kasama","Kasama-shi","Kashima-shi","Kasumigaura","Kasumigaura-shi","Katsuta","Kitaibaraki","Kitaibaraki-shi","Koga","Koga-shi","Makabe","Mito","Mito-shi","Mitsukaid\u014d","Moriya","Moriya-shi","Naka","Naka-gun","Namegata","Namegata-shi","\u014carai","Okunoya","Omitama-shi","\u014cmiya","Ry\u016bgasaki","Ry\u016bgasaki-shi","Sakai","Sakuragawa","Sakuragawa-shi","Shimodate","Shimotsuma-shi","Takahagi","Tomobe","Toride","Toride-shi","Tsuchiura-shi","Tsukuba","Tsukuba-shi","Tsukubamirai","Tsukubamirai-shi","Ushiku","Ushiku-shi","Y\u016bki","Y\u016bki-shi"]},{"name":"Ishikawa Prefecture","state_code":"17","cities":["Hakui","Hakui Shi","Hakusan Shi","Kaga Shi","Kahoku Shi","Kanazawa","Kanazawa-shi","Komatsu","Matsut\u014d","Nanao Shi","Nomi Shi","Nonoichi","Nonoichi-shi","Suzu","Suzu Shi","Tsubata","Tsurugi-asahimachi","Wajima Shi"]},{"name":"Iwate Prefecture","state_code":"03","cities":["Hachimantai","Hachimantai Shi","Hanamaki","Hanamaki Shi","Ichinohe","Ichinoseki","Ichinoseki-shi","Iwate-gun","Kamaishi","Kamaishi-shi","Kitakami","Kitakami-shi","Kuji","Kuji-shi","Miyako","Miyako-shi","Mizusawa","Morioka","Morioka-shi","Ninohe","Ninohe Shi","\u014cfunato","\u014cfunato-shi","\u014csh\u016b","\u014csh\u016b-shi","\u014ctsuchi","Rikuzentakata-shi","Shizukuishi","Takizawa-shi","T\u014dno","T\u014dno-shi","Yamada"]},{"name":"Kagawa Prefecture","state_code":"37","cities":["Higashikagawa Shi","Kan\u2019onji Shi","Kan\u2019onjich\u014d","Marugame","Marugame Shi","Mitoyo Shi","Sakaide Shi","Sakaidech\u014d","Sanuki-shi","Shido","Tadotsu","Takamatsu","Takamatsu Shi","Tonosh\u014d","Zents\u016bji Shi"]},{"name":"Kagoshima Prefecture","state_code":"46","cities":["Aira Shi","Akune","Akune Shi","Amami","Amami Shi","Hamanoichi","Hioki","Hioki Shi","Ibusuki","Ibusuki Shi","Ichikikushikino Shi","Ij\u016bin","Isa Shi","Izumi","Izumi Shi","Kagoshima","Kagoshima Shi","Kajiki","Kanoya","Kanoya Shi","Kaseda-shirakame","Kirishima Shi","Kokubu-matsuki","Koseda","Koshima","Kurio","Kushikino","Makurazaki","Makurazaki Shi","Minamikyushu Shi","Minamisatsuma Shi","Miyanoura","Nagata","Naze","Nishinoomote","Nishinoomote Shi","\u014ckuchi-shinohara","Satsumasendai","Satsumasendai Shi","Shibushi","Shibushi-shi","Soo Shi","Sueyoshich\u014d-ninokata","Tarumizu","Tarumizu Shi","Yudomari"]},{"name":"Kanagawa Prefecture","state_code":"14","cities":["Atsugi","Atsugi Shi","Ayase Shi","Chigasaki","Chigasaki Shi","Ebina Shi","Fujisawa","Fujisawa Shi","Hadano","Hadano-shi","Hakone","Hayama","Hiratsuka","Hiratsuka Shi","Isehara","Isehara Shi","Kamakura","Kamakura Shi","Kawasaki","Kawasaki-shi","Minamiashigara","Minamiashigara Shi","Minamirinkan","Miura","Miura Shi","Ninomiya","Odawara","Odawara-shi","\u014ciso","Sagamihara-shi","Yamakita","Yamato-shi","Yokohama","Yokohama Shi","Yokosuka","Yokosuka Shi","Yugawara","Zama","Zama Shi","Zushi Shi"]},{"name":"K\u014dchi Prefecture","state_code":"39","cities":["Achi","Agematsu","Aki","Anan","Aoki","Asahi","Azumino","Chikuhoku","Chikuma","Chino","Fujimi","Geisei","Hakuba","Hara","Hidaka","Hiraya","Iida","Iijima","Iiyama","Iizuna","Ikeda","Ikusaka","Ina","Ino","Karuizawa","Kawakami","Kijimadaira","Kiso","Kitaaiki","Kitagawa","K\u014dchi","Komoro","K\u014dnan","Kuroshio","Matsukawa","Matsumoto","Mihara","Minamiaiki","Minamimaki","Minamiminowa","Minowa","Mitsushima","Miyada","Miyota","Motoyama","Muroto","Nagano","Nagawa","Nagiso","Nahari","Nakagawa","Nakaj\u014d","Nakamura","Nakano","Nakatosa","Nankoku","Neba","Niyodogawa","Nozawaonsen","Obuse","Ochi","Ogawa","\u014ckawa","Okaya","\u014ckuwa","\u014cmachi","Omi","\u014cshika","\u014ctaki","Otari","\u014ctoyo","\u014ctsuki","Sakae","Sakaki","Sakawa","Saku","Sakuho","Sanada","Shimanto","Shimoj\u014d","Shimosuwa","Shinano","Shiojiri","Sukumo","Susaki","Suwa","Suzaka","Takagi","Takamori","Takayama","Tano","Tateshina","Tatsuno","Togari","T\u014dmi","Tosa","Tosashimizu","T\u014dy\u014d","Toyooka","Tsuno","Ueda","Umaji","Urugi","Usa","Yamagata","Yamanouchi","Yasuda","Yasuoka","Yawata","Yusuhara"]},{"name":"Kumamoto Prefecture","state_code":"43","cities":["Amakusa Gun","Amakusa Shi","Arao Shi","Aso-shi","Hitoyoshi","Hitoyoshi Shi","Hondomachi-hondo","Honmachi","Kamiamakusa Shi","Kikuchi","Kikuchi Shi","K\u014dshi Shi","Kumamoto","Kumamoto Shi","Matsubase","Minamata","Minamata Shi","\u014czu","Tamana","Tamana Shi","Uekimachi-m\u014dno","Uki Shi","Ushibukamachi","Uto","Uto Shi","Yamaga Shi","Yatsushiro Shi"]},{"name":"Ky\u014dto Prefecture","state_code":"26","cities":["Arashiyama","Ayabe","Ayabe-shi","Fukuchiyama-shi","J\u014dy\u014d Shi","Kameoka","Kameoka-shi","Kamigy\u014d-ku","Kizugawa-shi","Ky\u014dtanabe Shi","Ky\u014dtango-shi","Kyoto","Maizuru","Maizuru-shi","Miyazu","Miyazu-shi","Muk\u014d Shi","Nagaokaky\u014d Shi","Nantan-shi","Tanabe","Uji","Uji Shi","Yawata","Yawata Shi"]},{"name":"Mie Prefecture","state_code":"24","cities":["Hisai-motomachi","Iga-shi","Inabe","Inabe-shi","Ise","Ise-shi","Kameyama","Kameyama Shi","Kawage","Komono","Kumano","Kumano-shi","Kuwana","Kuwana-shi","Matsuzaka-shi","Nabari","Nabari-shi","Owase","Shima","Shima-shi","Suzuka","Suzuka-shi","Toba","Toba-shi","Tsu","Tsu-shi","Ueno-ebisumachi","Yokkaichi-shi"]},{"name":"Miyagi Prefecture","state_code":"04","cities":["Furukawa","Higashimatshushima Shi","Higashimatsushima","Ishinomaki","Ishinomaki Shi","Iwanuma","Iwanuma-shi","Kakuda","Kakuda Shi","Kesennuma","Kesennuma Shi","Kogota","Kurihara","Kurihara Shi","Marumori","Matsushima","Natori Shi","\u014ckawara","Onagawa Ch\u014d","\u014csaki","\u014csaki Shi","Rifu","Sendai","Shiogama","Shiroishi","Shiroishi Shi","Tagaj\u014d Shi","Tome Shi","Tomiya","Wakuya","Watari","Watari-gun","Yamoto"]},{"name":"Miyazaki Prefecture","state_code":"45","cities":["Ebino-shi","Hy\u016bga-shi","Kobayashi","Kobayashi Shi","Kushima","Kushima Shi","Miyakonoj\u014d","Miyakonoj\u014d Shi","Miyazaki","Miyazaki-shi","Nichinan","Nichinan Shi","Nobeoka","Nobeoka-shi","Saito-shi","Takanabe","Tsuma"]},{"name":"Nagano Prefecture","state_code":"20","cities":["Azumino-Shi","Chikuma Shi","Chino","Chino Shi","Hakuba","Hotaka","Iida","Iida-shi","Iiyama","Iiyama Shi","Ina","Ina-shi","Kamimaruko","Komagane","Komagane-shi","Komoro","Komoro Shi","Matsumoto","Matsumoto Shi","Nagano","Nagano Shi","Nakano Shi","Okaya","Okaya Shi","\u014cmachi","\u014cmachi-shi","Saku","Saku Shi","Shiojiri","Shiojiri-shi","Suwa","Suwa Shi","Suzaka","Suzaka-shi","Tatsuno","T\u014dmi","T\u014dmi Shi","Toyoshina","Ueda","Ueda Shi"]},{"name":"Nagasaki Prefecture","state_code":"42","cities":["Fukuech\u014d","Got\u014d Shi","Hirado","Hirado Shi","Iki Shi","Isahaya","Isahaya-shi","Matsuura","Matsuura Shi","Minamishimabara-shi","Nagasaki","Nagasaki-shi","Obita","\u014cmura","\u014cmura-shi","Saikai-shi","Sasebo Shi","Shimabara","Shimabara-shi","Togitsu","Tsushima Shi","Unzen-shi"]},{"name":"Nara Prefecture","state_code":"29","cities":["Goj\u014d","Goj\u014d-shi","Gose","Haibara-akanedai","H\u014dry\u016bji","Ikoma","Ikoma-shi","Kashiba-shi","Kashihara-shi","Katsuragi","Katsuragi Shi","Nara-shi","Sakurai","Sakurai-shi","Tawaramoto","Tenri","Tenri-shi","Uda Shi","Yamatok\u014driyama-shi","Yamatotakada-shi","Yoshino-ch\u014d"]},{"name":"Niigata Prefecture","state_code":"15","cities":["Agano Shi","Arai","Gosen","Gosen Shi","Itoigawa","Itoigawa Shi","J\u014detsu","J\u014detsu Shi","Kameda-honch\u014d","Kamo","Kamo Shi","Kashiwazaki","Kashiwazaki Shi","Maki","Minamiuonuma Shi","Mitsuke","Mitsuke Shi","Muikamachi","Murakami Shi","Muramatsu","Myoko-shi","Nagaoka","Nagaoka Shi","Niigata","Niigata Shi","Niitsu-honch\u014d","Ojiya","Ojiya-shi","Ry\u014dtsu-minato","Sado Shi","Sanj\u014d Shi","Shibata","Shibata Shi","Shiozawa","Shirone","Suibara","Tainai","Tainai Shi","Tochio-honch\u014d","T\u014dkamachi","T\u014dkamachi-shi","Tsubame","Tsubame Shi","Uonuma","Uonuma Shi","Yoshida-kasugach\u014d"]},{"name":"\u014cita Prefecture","state_code":"44","cities":["Beppu","Beppu Shi","Bungo-\u014dno Shi","Bungo-Takada-shi","Hiji","Hita","Hita Shi","Kitsuki","Kitsuki Shi","Kunisaki-shi","Nakatsu","Nakatsu Shi","\u014cita","\u014cita-shi","Saiki","Saiki-shi","Takedamachi","Taketa-shi","Tsukawaki","Tsukumi-shi","Tsukumiura","Tsurusaki","Usa Shi","Usuki","Usuki Shi","Yufu-shi"]},{"name":"Okayama Prefecture","state_code":"33","cities":["Akaiwa Shi","Asakuchi Shi","Bizen Shi","Ibara","Ibara Shi","Kamogatach\u014d-kamogata","Kasaoka","Kasaoka Shi","Kurashiki","Kurashiki Shi","Maniwa-shi","Mimasaka-shi","Niimi","Niimi Shi","Okayama","Okayama Shi","Setouchi Shi","S\u014dja","S\u014dja Shi","Takahashi","Takahashi Shi","Tamano","Tamano Shi","Tsuyama","Tsuyama-shi"]},{"name":"Okinawa Prefecture","state_code":"47","cities":["Chatan","Ginowan Shi","Gushikawa","Hirara","Ishigaki","Ishigaki-shi","Ishikawa","Itoman","Itoman Shi","Katsuren-haebaru","Miyakojima Shi","Nago","Nago Shi","Naha","Naha Shi","Nakagami-gun","Nanj\u014d","Nanj\u014d Shi","Okinawa","Okinawa Shi","Tomigusuku","Tomigusuku-shi","Urasoe Shi","Uruma Shi","Yonakuni"]},{"name":"\u014csaka Prefecture","state_code":"27","cities":["Dait\u014d Shi","Dait\u014dch\u014d","Fujiidera-shi","Habikino-shi","Hannan","Hannan Shi","Higashi\u014dsaka Shi","Hirakata","Hirakata Shi","Ibaraki","Ibaraki Shi","Ikeda","Ikeda Shi","Izumi","Izumi Shi","Izumi\u014dtsu","Izumi\u014dtsu Shi","Izumisano","Izumisano Shi","Kadoma","Kadoma Shi","Kaizuka","Kaizuka Shi","Kashihara","Kashiwara-shi","Katano Shi","Kawachi-nagano Shi","Kishiwada","Kishiwada Shi","Matsubara","Matsubara-shi","Mino","Minoo Shi","Mishima-gun","Moriguchi","Neyagawa","Neyagawa Shi","Osaka","\u014csaka-sayama Shi","Sakai","Sakai Shi","Sennan Shi","Settsu Shi","Shijonawate Shi","Suita","Suita Shi","Tajiri","Takaishi","Takaishi Shi","Takatsuki","Takatsuki Shi","Tondabayashi Shi","Tondabayashich\u014d","Toyonaka","Toyonaka Shi","Yao","Yao-shi"]},{"name":"Saga Prefecture","state_code":"41","cities":["Imari Shi","Imarich\u014d-k\u014d","Kanzaki Shi","Karatsu","Karatsu Shi","Kashima","Kashima Shi","Miyaki-gun","Ogi-shi","Saga","Saga Shi","Takeo Shi","Takeoch\u014d-takeo","Taku Shi","Tosu Shi","Ureshino Shi"]},{"name":"Saitama Prefecture","state_code":"11","cities":["Ageo Shi","Ageoshimo","Asaka","Asaka-shi","Chichibu","Chichibu-shi","Fujimi-shi","Fujimino Shi","Fukaya-shi","Fukayach\u014d","Fukiage-fujimi","Gy\u014dda","Hann\u014d","Hann\u014d-shi","Hany\u016b","Hany\u016b-shi","Hasuda","Hasuda-shi","Hatogaya-honch\u014d","Hidaka-shi","Higashimatsuyama Shi","Hiki-gun","Honj\u014d","Honj\u014d Shi","Iruma-shi","Iwatsuki","Kamifukuoka","Kasukabe","Kasukabe Shi","Kawagoe","Kawagoe-shi","Kawaguchi","Kawaguchi-shi","Kazo","Kazo-shi","Kisai","Kitamoto Shi","Kodamach\u014d-kodamaminami","K\u014dnosu","Konosu-Shi","Koshigaya Shi","Kuki-shi","Kukich\u016b\u014d","Kumagaya Shi","Kurihashi","Menuma","Misato Shi","Morohong\u014d","Niiza-shi","Ogawa","\u014ci","Okegawa","Okegawa-shi","\u014csato-gun","Saitama","Saitama-shi","Sakado","Sakado-shi","Satte","Satte Shi","Sayama","Shiki","Shiki Shi","Shimotoda","Shiraoka","Shiraoka-shi","Sh\u014dbu","S\u014dka","S\u014dka Shi","Sugito","Toda-shi","Tokorozawa","Tokorozawa-shi","Tsurugashima-shi","Wako","Wak\u014d-shi","Warabi-shi","Yashio","Yashio-shi","Yono","Yorii","Yoshikawa","Yoshikawa Shi"]},{"name":"Shiga Prefecture","state_code":"25","cities":["Higashi\u014dmi-shi","Hikone","Hikone-shi","Hino","Kitahama","K\u014dka-shi","Konan-shi","Kusatsu","Kusatsu-shi","Maibara","Maibara-shi","Minakuchich\u014d-matoba","Moriyama","Moriyama-shi","Nagahama","Nagahama-shi","\u014cmihachiman","\u014cmihachiman-shi","\u014ctsu-shi","Ritt\u014d-shi","Takashima","Takashima-shi","Yasu-shi","Youkaichi"]},{"name":"Shimane Prefecture","state_code":"32","cities":["G\u014dtsu Shi","G\u014dtsuch\u014d","Hamada","Hamada Shi","Hiratach\u014d","Izumo","Izumo Shi","Masuda","Masuda Shi","Matsue","Matsue Shi","\u014cda Shi","\u014cdach\u014d-\u014dda","Unnan Shi","Yasugi Shi","Yasugich\u014d"]},{"name":"Shizuoka Prefecture","state_code":"22","cities":["Atami","Atami-shi","Fuji Shi","Fujieda Shi","Fujinomiya","Fujinomiya Shi","Fukuroi","Fukuroi-shi","Gotenba Shi","Hamakita","Hamamatsu","Hamamatsu-shi","Heda","It\u014d","It\u014d Shi","Iwata","Iwata-shi","Izu","Izu-shi","Izunokuni-shi","Kakegawa","Kakegawa Shi","Kanaya","Kikugawa-shi","Kosai","Kosai-shi","Makinohara Shi","Mishima","Mishima Shi","Mori","Numazu-shi","Omaezaki-shi","\u014cyama","Sagara","Shimada","Shimada-shi","Shimoda","Shimoda-shi","Shizuoka","Shizuoka-shi","Susono","Susono Shi","Yaizu","Yaizu Shi"]},{"name":"Tochigi Prefecture","state_code":"09","cities":["Ashikaga","Fujioka","Imaichi","Kaminokawa","Kanuma","Kanuma-shi","Karasuyama","Kuroiso","Mashiko","Mibu","Mooka","Mooka-shi","Motegi","Nasukarasuyama","Nasukarasuyama-shi","Nasushiobara-shi","Nikk\u014d","Nikko-shi","\u014ctawara","\u014ctawara-shi","Oyama","Oyama-shi","Sakura-shi","Sano","Sano-shi","Shimotsuke-shi","Tanuma","Tochigi-shi","Ujiie","Utsunomiya","Utsunomiya-shi","Yaita","Yaita-shi"]},{"name":"Tokushima Prefecture","state_code":"36","cities":["Anan Shi","Awa-shi","Ikedach\u014d","Ishii","Kamojimach\u014d-j\u014dgejima","Katsuura Gun","Komatsushima Shi","Komatsushimach\u014d","Mima Shi","Miyoshi Shi","Miyoshi-gun","Naruto-shi","Narutoch\u014d-mitsuishi","Tokushima","Tokushima Shi","Wakimachi","Yoshinogawa Shi"]},{"name":"Tokyo","state_code":"13","cities":["Adachi Ku","Akiruno-shi","Akishima-shi","Arakawa Ku","Bunky\u014d-ku","Chiyoda-ku","Ch\u014dfu","Ch\u014dfu-shi","Ch\u016b\u014d Ku","Edogawa Ku","Fuch\u016b-shi","Fussa","Hachi\u014dji","Hamura-shi","Higashi-murayama-shi","Higashikurume-shi","Higashimurayama","Higashiyamato","Higashiyamato-shi","Hino","Hino-shi","Inagi-shi","Itabashi-ku","Itsukaichi","Kamirenjaku","Katsushika Ku","Kita-ku","Kiyose-shi","Kodaira-shi","Koganei-shi","Kokubunji","Kokubunji-shi","Komae-shi","K\u014dt\u014d-ku","Kunitachi-shi","Machida","Machida-shi","Meguro-ku","Minato-ku","Mitaka-shi","Musashimurayama-shi","Musashino","Musashino-shi","Nakano-ku","Nerima-ku","Nishi-Tokyo-shi","Nishit\u014dky\u014d-shi","\u014cme","\u014cme-shi","\u014cta-ku","Setagaya-ku","Shibuya-ku","Shinagawa-ku","Shinjuku-ku","Suginami-ku","Sumida-ku","Tachikawa-shi","Tait\u014d-ku","Tama-shi","Tanashich\u014d","Tokyo","Toshima-ku","Urayasu"]},{"name":"Tottori Prefecture","state_code":"31","cities":["Kurayoshi-shi","Sakaiminato","Sakaiminato Shi","Tottori-shi","Yonago Shi"]},{"name":"Toyama Prefecture","state_code":"16","cities":["Fukumitsu","Himi Shi","Himimachi","Imizu Shi","Kamiichi","Kurobe-shi","Namerikawa","Namerikawa-shi","Nanto Shi","Nanto-shi","Nishishinminato","Ny\u016bzen","Oyabe","Oyabe Shi","Takaoka","Takaoka Shi","Tonami Shi","Toyama Shi","Uozu","Uozu Shi","Yatsuomachi-higashikumisaka"]},{"name":"Wakayama Prefecture","state_code":"30","cities":["Arida Shi","Gob\u014d","Hashimoto","Hashimoto Shi","Iwade","Iwade Shi","Kainan","Kainan Shi","Kinokawa Shi","K\u014dya","Minato","Shing\u016b","Shing\u016b-shi","Tanabe-shi","Wakayama","Wakayama Shi"]},{"name":"Yamagata Prefecture","state_code":"06","cities":["Higashine","Higashine Shi","Kaminoyama","Kaminoyama-shi","Murayama","Murayama Shi","Nagai","Nagai-shi","Nany\u014d Shi","Obanazawa","Obanazawa Shi","Sagae","Sagae-shi","Sakata","Sakata Shi","Shinj\u014d","Shinj\u014d Shi","Takahata","Tend\u014d","Tend\u014d Shi","Tsuruoka","Tsuruoka Shi","Yamagata","Yamagata Shi","Yonezawa","Yonezawa Shi","Yuza"]},{"name":"Yamaguchi Prefecture","state_code":"35","cities":["Hagi","Hagi Shi","Hikari","Hikari Shi","H\u014dfu","Hofu Shi","Iwakuni Shi","Kudamatsu","Kudamatsu Shi","Mine Shi","Nagato","Nagato Shi","Og\u014dri-shimog\u014d","Onoda","Sany\u014donoda Shi","Shimonoseki Shi","Sh\u016bnan Shi","Tokuyama","Ube","Yamaguchi Shi","Yanai Shi"]},{"name":"Yamanashi Prefecture","state_code":"19","cities":["Ch\u016b\u014d-shi","Enzan","Fuefuki-shi","Fuji-yoshida Shi","Fujikawaguchiko","Fujiyoshida","Hokuto","Hokuto-shi","Isawa","Kai-shi","K\u014dfu","K\u014dfu-shi","K\u014dsh\u016b-shi","Minami Alps-shi","Nirasaki","Nirasaki-shi","\u014ctsuki","\u014ctsuki-shi","Ry\u016b\u014d","Tsuru-shi","Uenohara","Uenohara-shi","Yamanashi-shi"]}]}