{"name":"Paraguay","iso3":"PRY","iso2":"PY","phone_code":"595","capital":"Asuncion","currency":"PYG","currency_name":"Paraguayan guarani","currency_symbol":"\u20b2","emoji":"\ud83c\uddf5\ud83c\uddfe","emojiU":"U+1F1F5 U+1F1FE","translations":{"kr":"\ud30c\ub77c\uacfc\uc774","br":"Paraguai","pt":"Paraguai","nl":"Paraguay","hr":"Paragvaj","fa":"\u067e\u0627\u0631\u0627\u06af\u0648\u0626\u0647","de":"Paraguay","es":"Paraguay","fr":"Paraguay","ja":"\u30d1\u30e9\u30b0\u30a2\u30a4","it":"Paraguay","cn":"\u5df4\u62c9\u572d","tr":"Paraguay"},"states":[{"name":"Alto Paraguay Department","state_code":"16","cities":["Capit\u00e1n Pablo Lagerenza","Fuerte Olimpo"]},{"name":"Alto Paran\u00e1 Department","state_code":"10","cities":["Cedrales","Ciudad del Este","Colonia Minga Por\u00e1","Doctor Juan Le\u00f3n Mallorqu\u00edn","Itakyry","Naranjal","Presidente Franco","San Alberto","Santa Rita","Yguaz\u00fa"]},{"name":"Amambay Department","state_code":"13","cities":["Bella Vista","Capit\u00e1n Bado","Pedro Juan Caballero"]},{"name":"Boquer\u00f3n Department","state_code":"19","cities":["Colonia Menno","Colonia Neuland","Filadelfia"]},{"name":"Caaguaz\u00fa","state_code":"5","cities":["Caaguaz\u00fa","Caraya\u00f3","Cecilio Baez","Colonia General Alfredo Stroessner","Coronel Oviedo","Doctor Juan Manuel Frutos","Mbutu\u00fd","Repatriaci\u00f3n","San Joaqu\u00edn","San Jos\u00e9","Yh\u00fa"]},{"name":"Caazap\u00e1","state_code":"6","cities":["Aba\u00ed","Buena Vista","Caazap\u00e1","General Higinio Mor\u00ednigo","San Juan Nepomuceno","Yegros","Yuty"]},{"name":"Canindey\u00fa","state_code":"14","cities":["Colonia Catuete","Corpus Christi","La Paloma","Nueva Esperanza","Salto del Guair\u00e1","San Isidro de Curuguaty","Ygatimi"]},{"name":"Central Department","state_code":"11","cities":["Aregu\u00e1","Capiat\u00e1","Fernando de la Mora","Guarambar\u00e9","It\u00e1","Itaugu\u00e1","Lambar\u00e9","Limpio","Mariano Roque Alonso","Nemby","Nueva Italia","San Antonio","San Lorenzo","Villa Elisa","Ypacarai"]},{"name":"Concepci\u00f3n Department","state_code":"1","cities":["Bel\u00e9n","Concepci\u00f3n","Horqueta"]},{"name":"Cordillera Department","state_code":"3","cities":["Altos","Arroyos y Esteros","Atyr\u00e1","Caacup\u00e9","Caraguatay","Emboscada","Eusebio Ayala","Isla Puc\u00fa","Itacurub\u00ed de la Cordillera","Piribebuy","San Bernardino","Santa Elena","Tobat\u00ed"]},{"name":"Guair\u00e1 Department","state_code":"4","cities":["Colonia Mauricio Jos\u00e9 Troche","Coronel Mart\u00ednez","Independencia","Itap\u00e9","Iturbe","Mbocayaty","Natalicio Talavera","Villarrica"]},{"name":"Itap\u00faa","state_code":"7","cities":["Arquitecto Tom\u00e1s Romero Pereira","Bella Vista","Capit\u00e1n Miranda","Carmen del Paran\u00e1","Colonia Carlos Antonio L\u00f3pez","Colonia San Lorenzo","Edelira","Encarnaci\u00f3n","Fram","General Artigas","General Delgado","Hohenau","Jes\u00fas","Natalio","Obligado","Pirap\u00f3","Puerto Mayor Ota\u00f1o","San Cosme y Dami\u00e1n","San Juan del Paran\u00e1","San Pedro del Paran\u00e1","Trinidad"]},{"name":"Misiones Department","state_code":"8","cities":["Juan de Ayolas","San Juan Bautista","San Miguel","San Patricio","Santa Mar\u00eda","Santa Rosa Misiones","Santiago","Villa Florida"]},{"name":"\u00d1eembuc\u00fa Department","state_code":"12","cities":["Cerrito","General Jos\u00e9 Eduvigis D\u00edaz","Pilar"]},{"name":"Paraguar\u00ed Department","state_code":"9","cities":["Acahay","Caapuc\u00fa","Carapegu\u00e1","La Colmena","Mbuyapey","Paraguar\u00ed","Piray\u00fa","Quiindy","Sapuca\u00ed","Yaguar\u00f3n","Ybycu\u00ed"]},{"name":"Presidente Hayes Department","state_code":"15","cities":["Benjam\u00edn Aceval","Nanawua","Villa Hayes"]},{"name":"San Pedro Department","state_code":"2","cities":["Antequera","Capi\u00edbary","Colonia Nueva Germania","General Elizardo Aquino","Guayaybi","Itacurub\u00ed del Rosario","Lima","Puerto Rosario","San Pedro de Ycuamandiy\u00fa","Tacuat\u00ed","Uni\u00f3n","Yataity del Norte"]}]}